stamps/__init__.py
stamps/run_aot_compile.py
stamps/aot/__init__.py
stamps/aot/general/__init__.py
stamps/bme/BMEoptions.py
stamps/bme/BMEprobaEstimations.py
stamps/bme/__init__.py
stamps/bme/pystks_variable.py
stamps/bme/softconverter.py
stamps/general/__init__.py
stamps/general/bobyqa.py
stamps/general/coord2K.py
stamps/general/coord2dist.py
stamps/general/diffarray.py
stamps/general/diffarray__aot.py
stamps/general/findpairs.py
stamps/general/findzfromgriddata.py
stamps/general/isspacetime.py
stamps/general/neighbours.py
stamps/general/ortho.py
stamps/general/outlier_detection.py
stamps/general/pso.py
stamps/general/tensor.py
stamps/general/valstvgx.py
stamps/graph/__init__.py
stamps/graph/dataplot.py
stamps/graph/modelplot.py
stamps/graph/normal_distribution_plot.py
stamps/graph/pdfplot.py
stamps/graph/shpplot.py
stamps/models/__init__.py
stamps/models/covmodel.py
stamps/mvn/__init__.py
stamps/mvn/latticeseq_b2.py
stamps/mvn/qmc.py
stamps/stats/__init__.py
stamps/stats/anisotropy.py
stamps/stats/dlnm.py
stamps/stats/ent.py
stamps/stats/eof.py
stamps/stats/gam.py
stamps/stats/hosvd.py
stamps/stats/mepdf.py
stamps/stats/mlecovfit.py
stamps/stats/simuce.py
stamps/stats/simuchol.py
stamps/stats/stcov.py
stamps/stats/stcovfit.py
stamps/stats/stl.py
stamps/stest/__init__.py
stamps/stest/designmatrix.py
stamps/stest/idw.py
stamps/stest/kernelsmoothing.py
stamps/stest/kernelsmoothing_truncate.py
stamps/stest/kriging.py
stamps/stest/localmeanBME.py
stamps/stest/regression.py
stamps/stest/stmean.py
stamps-0.1.2.dist-info/LICENSE.txt
stamps-0.1.2.dist-info/METADATA
stamps-0.1.2.dist-info/RECORD
stamps-0.1.2.dist-info/WHEEL
stamps-0.1.2.dist-info/top_level.txt
