Metadata-Version: 2.1
Name: stamps
Version: 0.1.2
Summary: Spatial Temporal Analysis and Mapping Python Suite
Home-page: https://github.com/stemlab689/stamps
Author: stemlab
Author-email: stemlab689@gmail.com
License: MIT
Download-URL: https://gitlab.com/STEMLabTW/stamps/-/archive/0.1.2/stamps-0.1.2.zip
Keywords: analysis mapping stamps
Platform: UNKNOWN
Classifier: Development Status :: 3 - Alpha
Classifier: License :: OSI Approved :: MIT License
Classifier: Programming Language :: Python :: 2
Classifier: Programming Language :: Python :: 2.6
Classifier: Programming Language :: Python :: 2.7
Classifier: Programming Language :: Python :: 3
Classifier: Programming Language :: Python :: 3.4
Classifier: Programming Language :: Python :: 3.5
Classifier: Programming Language :: Python :: 3.6
Requires-Dist: numpy (>=1.13)
Requires-Dist: scipy (>=0.15)
Requires-Dist: pandas (>=0.22)
Requires-Dist: six (>=1.11)
